pytrader/MarkeDataEntity_pb2.py
pytrader/MarketData.py
pytrader/__init__.py
pytrader/filetime.py
ptrader_py-0.2.0.dist-info/LICENSE.txt
ptrader_py-0.2.0.dist-info/METADATA
ptrader_py-0.2.0.dist-info/WHEEL
ptrader_py-0.2.0.dist-info/top_level.txt
ptrader_py-0.2.0.dist-info/RECORD
