Metadata-Version: 2.1
Name: ptrader-py
Version: 0.2.0
Home-page: 
Author: Pedro Puado
Author-email: ppuado@gmail.com
License: MIT
Classifier: License :: OSI Approved :: MIT License
Classifier: Programming Language :: Python :: 3.11
Classifier: Operating System :: OS Independent
Requires-Python: >=3.11
License-File: LICENSE.txt
Requires-Dist: pandas >=2.1.4
Requires-Dist: protobuf >=4.25.1
